coauthor_finder/__init__.py
coauthor_finder/find_coauthors.py
coauthor_finder-0.1.dist-info/METADATA
coauthor_finder-0.1.dist-info/WHEEL
coauthor_finder-0.1.dist-info/top_level.txt
coauthor_finder-0.1.dist-info/RECORD
