Metadata-Version: 2.1
Name: coauthor-finder
Version: 0.1
Summary: A simple tool to list all your coauthors and the year of lastest collaboration.
Home-page: https://github.com/ChenLiu-1996/CoauthorFinder
Author: Chen Liu
Author-email: chen.liu.cl2482@yale.edu
License: CC BY-NC-SA
Keywords: coauthor,google scholar
Classifier: Development Status :: 3 - Alpha
Classifier: Intended Audience :: Developers
Classifier: License :: Other/Proprietary License
Classifier: Programming Language :: Python :: 3
Requires-Dist: scholarly
Requires-Dist: tqdm
Requires-Dist: pandas
